{"dependencies":[{"name":"C:\\Users\\Bob\\Desktop\\pets\\package.json","includedInParent":true,"mtime":1530669347970},{"name":"./style.css","dynamic":true,"parent":"C:\\Users\\Bob\\Desktop\\pets\\index.html","resolved":"C:\\Users\\Bob\\Desktop\\pets\\style.css"},{"name":"./main.js","dynamic":true,"parent":"C:\\Users\\Bob\\Desktop\\pets\\index.html","resolved":"C:\\Users\\Bob\\Desktop\\pets\\main.js"}],"generated":{"html":"<!DOCTYPE html>\r\n<html>\r\n\r\n<head>\r\n    <meta name=\"theme-color\" content=\"#1976d2\">\r\n    <link rel=\"icon\" type=\"image/x-icon\" href=\"http://bobd.me/pets/favicon.png\">\r\n\r\n  <link href=\"https://fonts.googleapis.com/css?family=Roboto:300,400,500,700|Material+Icons\" rel=\"stylesheet\">\r\n  <link href=\"https://unpkg.com/vuetify/dist/vuetify.min.css\" rel=\"stylesheet\">\r\n  <meta name=\"viewport\" content=\"width=device-width, initial-scale=1, maximum-scale=1, user-scalable=no, minimal-ui\">\r\n  <title>Adopt A Pet Finder - Bob Dempsey</title>\r\n  <link rel=\"stylesheet\" href=\"/aa52f528aeed60b2f2b667d049959436.css\">\r\n</head>\r\n\r\n<body>\r\n  <div id=\"app\">\r\n    <v-app>\r\n      <v-content>\r\n        <v-card flat=\"\">\r\n          <v-toolbar color=\"primary\" dark=\"\" extended=\"\" flat=\"\">\r\n            <v-toolbar-title class=\"white--text pt-3\">Adopt A Pet Finder - Bob Dempsey</v-toolbar-title>\r\n            <!-- <v-toolbar-side-icon></v-toolbar-side-icon> -->\r\n          </v-toolbar>\r\n\r\n          <v-layout row=\"\" pb-2=\"\">\r\n            <v-flex xs10=\"\" offset-xs1=\"\" md6=\"\" offset-md3=\"\">\r\n              <v-card class=\"card--flex-toolbar\">\r\n                <v-toolbar card=\"\" prominent=\"\">\r\n                  <v-toolbar-title class=\"body-2 grey--text\">Search For Your Pet</v-toolbar-title>\r\n                </v-toolbar>\r\n\r\n                <v-card-text>\r\n                  <v-form ref=\"form\" v-model=\"valid\" lazy-validation=\"\" id=\"petForm\">\r\n\r\n                    <v-select v-model=\"select\" :items=\"animals\" :rules=\"[v => !!v || 'Animal is required']\" label=\"Animal\" required=\"\" id=\"animal\"></v-select>\r\n\r\n                    <v-text-field v-model=\"zip\" :counter=\"5\" label=\"Zip Code\" required=\"\" clearable=\"\" :mask=\"mask\" :rules=\"[v => !!v || 'Zip Code is required']\" id=\"zip\" v-on:keyup.enter=\"fetchAnimals\"></v-text-field>\r\n\r\n                    <v-btn :disabled=\"!valid\" @click=\"fetchAnimals\" color=\"primary\" style=\"letter-spacing: 1.25px\">\r\n                      Find Pets!\r\n                    </v-btn>\r\n                    <v-btn @click=\"clear\">clear</v-btn>\r\n                  </v-form>\r\n\r\n              </v-card-text></v-card>\r\n              <v-alert :value=\"true\" type=\"error\" class=\"mt-3\" id=\"alert\">\r\n                Please Enter a Valid Zip Code\r\n              </v-alert>\r\n          </v-flex></v-layout>\r\n\r\n\r\n          <v-layout row=\"\" pb-2=\"\">\r\n            <v-flex xs10=\"\" offset-xs1=\"\" md10=\"\" offset-md1=\"\">\r\n              <div id=\"results\" class=\"mt-4\"></div>\r\n            </v-flex>\r\n          </v-layout>\r\n      </v-card></v-content>\r\n\r\n\r\n\r\n      <v-footer height=\"auto\" color=\"primary\">\r\n        <v-layout justify-center=\"\" row=\"\" wrap=\"\">\r\n          <v-flex primary=\"\" text-xs-center=\"\" white--text=\"\" xs12=\"\">\r\n            &copy;2018 —\r\n            <strong>\r\n              <a href=\"https://bobd.me\" style=\"color:#fff;text-decoration: none;\">BobD.me</a>\r\n            </strong>\r\n\r\n\r\n            <v-dialog v-model=\"dialog\" width=\"500\">\r\n              <v-btn slot=\"activator\" dark=\"\" fab=\"\">\r\n                <v-icon>info</v-icon>\r\n              </v-btn>\r\n\r\n              <v-card>\r\n                <v-card-title class=\"headline grey lighten-2\" primary-title=\"\">\r\n                  About This Web Application\r\n                </v-card-title>\r\n\r\n                <v-card-text>\r\n                  This web application is built with the PetFinder public data api, Vue JS, Vuetify, & fetchJsonP.\r\n                </v-card-text>\r\n\r\n                <v-divider></v-divider>\r\n\r\n                <v-card-actions>\r\n                  <v-spacer></v-spacer>\r\n                  <v-btn color=\"primary\" flat=\"\" @click=\"dialog = false\">\r\n                    Awesome!\r\n                  </v-btn>\r\n                </v-card-actions>\r\n              </v-card>\r\n            </v-dialog>\r\n\r\n          </v-flex>\r\n        </v-layout>\r\n      </v-footer>\r\n\r\n    </v-app>\r\n  </div>\r\n\r\n  <script src=\"https://unpkg.com/vue/dist/vue.js\"></script>\r\n  <script src=\"https://unpkg.com/vuetify/dist/vuetify.js\"></script>\r\n  <script src=\"/b3b9e7cca65264866b7f13acc54329eb.js\"></script>\r\n</body>\r\n\r\n</html>"},"hash":"3041eaa11ea2d13b05b281ab3dcf068c","cacheData":{},"id":1}